{
  "conditions": [
    {
      "type": "c:mod_loaded",
      "modid": "farmersdelight"
    },
    {
      "type": "c:mod_loaded",
      "modid": "quark"
    }
  ],
  "type": "minecraft:crafting_shapeless",
  "category": "misc",
  "ingredients": [
    {
      "item": "quark:moss_paste"
    },
    {
      "item": "quark:moss_paste"
    },
    {
      "item": "minecraft:glow_berries"
    },
    {
      "item": "minecraft:bowl"
    }
  ],
  "result": {
    "id": "quarkdelight:lush_moss_salad"
  }
}
